{"nodes": [{"id": "src_auth_oidc_rs", "label": "oidc.rs", "file_type": "code", "source_file": "src/auth/oidc.rs", "source_location": "L1"}, {"id": "oidc_oidcconfig", "label": "OidcConfig", "file_type": "code", "source_file": "src/auth/oidc.rs", "source_location": "L20"}, {"id": "oidc_oidcdiscovery", "label": "OidcDiscovery", "file_type": "code", "source_file": "src/auth/oidc.rs", "source_location": "L37"}, {"id": "oidc_tokenresponse", "label": "TokenResponse", "file_type": "code", "source_file": "src/auth/oidc.rs", "source_location": "L54"}, {"id": "oidc_oidcsession", "label": "OidcSession", "file_type": "code", "source_file": "src/auth/oidc.rs", "source_location": "L73"}, {"id": "oidc_new_session_store", "label": "new_session_store()", "file_type": "code", "source_file": "src/auth/oidc.rs", "source_location": "L96"}, {"id": "oidc_sweep_expired_sessions", "label": "sweep_expired_sessions()", "file_type": "code", "source_file": "src/auth/oidc.rs", "source_location": "L109"}, {"id": "oidc_spawn_session_cleanup", "label": "spawn_session_cleanup()", "file_type": "code", "source_file": "src/auth/oidc.rs", "source_location": "L121"}, {"id": "oidc_discover", "label": "discover()", "file_type": "code", "source_file": "src/auth/oidc.rs", "source_location": "L148"}, {"id": "oidc_new_pkce_verifier_store", "label": "new_pkce_verifier_store()", "file_type": "code", "source_file": "src/auth/oidc.rs", "source_location": "L165"}, {"id": "oidc_generate_code_verifier", "label": "generate_code_verifier()", "file_type": "code", "source_file": "src/auth/oidc.rs", "source_location": "L170"}, {"id": "oidc_compute_code_challenge", "label": "compute_code_challenge()", "file_type": "code", "source_file": "src/auth/oidc.rs", "source_location": "L179"}, {"id": "oidc_authorization_url", "label": "authorization_url()", "file_type": "code", "source_file": "src/auth/oidc.rs", "source_location": "L190"}, {"id": "oidc_authorization_url_with_pkce", "label": "authorization_url_with_pkce()", "file_type": "code", "source_file": "src/auth/oidc.rs", "source_location": "L195"}, {"id": "oidc_exchange_code", "label": "exchange_code()", "file_type": "code", "source_file": "src/auth/oidc.rs", "source_location": "L232"}, {"id": "oidc_exchange_code_with_pkce", "label": "exchange_code_with_pkce()", "file_type": "code", "source_file": "src/auth/oidc.rs", "source_location": "L241"}, {"id": "oidc_check_session", "label": "check_session()", "file_type": "code", "source_file": "src/auth/oidc.rs", "source_location": "L300"}, {"id": "oidc_refresh_session", "label": "refresh_session()", "file_type": "code", "source_file": "src/auth/oidc.rs", "source_location": "L344"}, {"id": "oidc_check_session_async", "label": "check_session_async()", "file_type": "code", "source_file": "src/auth/oidc.rs", "source_location": "L401"}, {"id": "oidc_session_matches_issuer", "label": "session_matches_issuer()", "file_type": "code", "source_file": "src/auth/oidc.rs", "source_location": "L463"}, {"id": "oidc_generate_session_id", "label": "generate_session_id()", "file_type": "code", "source_file": "src/auth/oidc.rs", "source_location": "L471"}, {"id": "oidc_extract_cookie", "label": "extract_cookie()", "file_type": "code", "source_file": "src/auth/oidc.rs", "source_location": "L482"}, {"id": "oidc_extract_sub_from_id_token", "label": "extract_sub_from_id_token()", "file_type": "code", "source_file": "src/auth/oidc.rs", "source_location": "L505"}, {"id": "oidc_urlencoded", "label": "urlencoded()", "file_type": "code", "source_file": "src/auth/oidc.rs", "source_location": "L523"}, {"id": "oidc_test_config", "label": "test_config()", "file_type": "code", "source_file": "src/auth/oidc.rs", "source_location": "L538"}, {"id": "oidc_test_discovery", "label": "test_discovery()", "file_type": "code", "source_file": "src/auth/oidc.rs", "source_location": "L548"}, {"id": "oidc_test_authorization_url_contains_params", "label": "test_authorization_url_contains_params()", "file_type": "code", "source_file": "src/auth/oidc.rs", "source_location": "L558"}, {"id": "oidc_test_authorization_url_default_scopes", "label": "test_authorization_url_default_scopes()", "file_type": "code", "source_file": "src/auth/oidc.rs", "source_location": "L568"}, {"id": "oidc_test_new_session_store_empty", "label": "test_new_session_store_empty()", "file_type": "code", "source_file": "src/auth/oidc.rs", "source_location": "L576"}, {"id": "oidc_test_check_session_no_cookie", "label": "test_check_session_no_cookie()", "file_type": "code", "source_file": "src/auth/oidc.rs", "source_location": "L582"}, {"id": "oidc_test_check_session_invalid_session_id", "label": "test_check_session_invalid_session_id()", "file_type": "code", "source_file": "src/auth/oidc.rs", "source_location": "L591"}, {"id": "oidc_test_check_session_valid", "label": "test_check_session_valid()", "file_type": "code", "source_file": "src/auth/oidc.rs", "source_location": "L603"}, {"id": "oidc_test_check_session_expired", "label": "test_check_session_expired()", "file_type": "code", "source_file": "src/auth/oidc.rs", "source_location": "L634"}, {"id": "oidc_test_extract_sub_from_id_token", "label": "test_extract_sub_from_id_token()", "file_type": "code", "source_file": "src/auth/oidc.rs", "source_location": "L658"}, {"id": "oidc_test_extract_sub_from_id_token_malformed", "label": "test_extract_sub_from_id_token_malformed()", "file_type": "code", "source_file": "src/auth/oidc.rs", "source_location": "L671"}, {"id": "oidc_test_urlencoded", "label": "test_urlencoded()", "file_type": "code", "source_file": "src/auth/oidc.rs", "source_location": "L676"}, {"id": "oidc_test_generate_session_id_length", "label": "test_generate_session_id_length()", "file_type": "code", "source_file": "src/auth/oidc.rs", "source_location": "L683"}, {"id": "oidc_test_generate_session_id_unique", "label": "test_generate_session_id_unique()", "file_type": "code", "source_file": "src/auth/oidc.rs", "source_location": "L689"}, {"id": "oidc_test_extract_cookie_present", "label": "test_extract_cookie_present()", "file_type": "code", "source_file": "src/auth/oidc.rs", "source_location": "L696"}, {"id": "oidc_test_extract_cookie_absent", "label": "test_extract_cookie_absent()", "file_type": "code", "source_file": "src/auth/oidc.rs", "source_location": "L706"}, {"id": "oidc_test_session_matches_issuer_exact", "label": "test_session_matches_issuer_exact()", "file_type": "code", "source_file": "src/auth/oidc.rs", "source_location": "L712"}, {"id": "oidc_test_session_matches_issuer_rejects_missing_issuer", "label": "test_session_matches_issuer_rejects_missing_issuer()", "file_type": "code", "source_file": "src/auth/oidc.rs", "source_location": "L726"}, {"id": "oidc_test_session_refresh_token_stored", "label": "test_session_refresh_token_stored()", "file_type": "code", "source_file": "src/auth/oidc.rs", "source_location": "L740"}, {"id": "oidc_test_session_without_refresh_token", "label": "test_session_without_refresh_token()", "file_type": "code", "source_file": "src/auth/oidc.rs", "source_location": "L755"}, {"id": "oidc_test_session_serialization_with_refresh_token", "label": "test_session_serialization_with_refresh_token()", "file_type": "code", "source_file": "src/auth/oidc.rs", "source_location": "L769"}, {"id": "oidc_test_session_deserialization_without_refresh_token", "label": "test_session_deserialization_without_refresh_token()", "file_type": "code", "source_file": "src/auth/oidc.rs", "source_location": "L785"}, {"id": "oidc_test_check_session_async_expired_no_refresh", "label": "test_check_session_async_expired_no_refresh()", "file_type": "code", "source_file": "src/auth/oidc.rs", "source_location": "L793"}, {"id": "oidc_test_generate_code_verifier_length", "label": "test_generate_code_verifier_length()", "file_type": "code", "source_file": "src/auth/oidc.rs", "source_location": "L819"}, {"id": "oidc_test_generate_code_verifier_unique", "label": "test_generate_code_verifier_unique()", "file_type": "code", "source_file": "src/auth/oidc.rs", "source_location": "L826"}, {"id": "oidc_test_compute_code_challenge_s256", "label": "test_compute_code_challenge_s256()", "file_type": "code", "source_file": "src/auth/oidc.rs", "source_location": "L833"}, {"id": "oidc_test_authorization_url_with_pkce_includes_challenge", "label": "test_authorization_url_with_pkce_includes_challenge()", "file_type": "code", "source_file": "src/auth/oidc.rs", "source_location": "L843"}, {"id": "oidc_test_authorization_url_without_pkce_no_challenge", "label": "test_authorization_url_without_pkce_no_challenge()", "file_type": "code", "source_file": "src/auth/oidc.rs", "source_location": "L858"}, {"id": "oidc_test_pkce_verifier_store_operations", "label": "test_pkce_verifier_store_operations()", "file_type": "code", "source_file": "src/auth/oidc.rs", "source_location": "L864"}], "edges": [{"source": "src_auth_oidc_rs", "target": "dashmap", "relation": "imports_from", "confidence": "EXTRACTED", "source_file": "src/auth/oidc.rs", "source_location": "L7", "weight": 1.0}, {"source": "src_auth_oidc_rs", "target": "hyper", "relation": "imports_from", "confidence": "EXTRACTED", "source_file": "src/auth/oidc.rs", "source_location": "L8", "weight": 1.0}, {"source": "src_auth_oidc_rs", "target": "serde", "relation": "imports_from", "confidence": "EXTRACTED", "source_file": "src/auth/oidc.rs", "source_location": "L9", "weight": 1.0}, {"source": "src_auth_oidc_rs", "target": "arc", "relation": "imports_from", "confidence": "EXTRACTED", "source_file": "src/auth/oidc.rs", "source_location": "L10", "weight": 1.0}, {"source": "src_auth_oidc_rs", "target": "debug", "relation": "imports_from", "confidence": "EXTRACTED", "source_file": "src/auth/oidc.rs", "source_location": "L11", "weight": 1.0}, {"source": "src_auth_oidc_rs", "target": "authresult", "relation": "imports_from", "confidence": "EXTRACTED", "source_file": "src/auth/oidc.rs", "source_location": "L13", "weight": 1.0}, {"source": "src_auth_oidc_rs", "target": "oidc_oidcconfig", "relation": "contains", "confidence": "EXTRACTED", "source_file": "src/auth/oidc.rs", "source_location": "L20", "weight": 1.0}, {"source": "src_auth_oidc_rs", "target": "oidc_oidcdiscovery", "relation": "contains", "confidence": "EXTRACTED", "source_file": "src/auth/oidc.rs", "source_location": "L37", "weight": 1.0}, {"source": "src_auth_oidc_rs", "target": "oidc_tokenresponse", "relation": "contains", "confidence": "EXTRACTED", "source_file": "src/auth/oidc.rs", "source_location": "L54", "weight": 1.0}, {"source": "src_auth_oidc_rs", "target": "oidc_oidcsession", "relation": "contains", "confidence": "EXTRACTED", "source_file": "src/auth/oidc.rs", "source_location": "L73", "weight": 1.0}, {"source": "src_auth_oidc_rs", "target": "oidc_new_session_store", "relation": "contains", "confidence": "EXTRACTED", "source_file": "src/auth/oidc.rs", "source_location": "L96", "weight": 1.0}, {"source": "src_auth_oidc_rs", "target": "oidc_sweep_expired_sessions", "relation": "contains", "confidence": "EXTRACTED", "source_file": "src/auth/oidc.rs", "source_location": "L109", "weight": 1.0}, {"source": "src_auth_oidc_rs", "target": "oidc_spawn_session_cleanup", "relation": "contains", "confidence": "EXTRACTED", "source_file": "src/auth/oidc.rs", "source_location": "L121", "weight": 1.0}, {"source": "src_auth_oidc_rs", "target": "oidc_discover", "relation": "contains", "confidence": "EXTRACTED", "source_file": "src/auth/oidc.rs", "source_location": "L148", "weight": 1.0}, {"source": "src_auth_oidc_rs", "target": "oidc_new_pkce_verifier_store", "relation": "contains", "confidence": "EXTRACTED", "source_file": "src/auth/oidc.rs", "source_location": "L165", "weight": 1.0}, {"source": "src_auth_oidc_rs", "target": "oidc_generate_code_verifier", "relation": "contains", "confidence": "EXTRACTED", "source_file": "src/auth/oidc.rs", "source_location": "L170", "weight": 1.0}, {"source": "src_auth_oidc_rs", "target": "oidc_compute_code_challenge", "relation": "contains", "confidence": "EXTRACTED", "source_file": "src/auth/oidc.rs", "source_location": "L179", "weight": 1.0}, {"source": "src_auth_oidc_rs", "target": "oidc_authorization_url", "relation": "contains", "confidence": "EXTRACTED", "source_file": "src/auth/oidc.rs", "source_location": "L190", "weight": 1.0}, {"source": "src_auth_oidc_rs", "target": "oidc_authorization_url_with_pkce", "relation": "contains", "confidence": "EXTRACTED", "source_file": "src/auth/oidc.rs", "source_location": "L195", "weight": 1.0}, {"source": "src_auth_oidc_rs", "target": "oidc_exchange_code", "relation": "contains", "confidence": "EXTRACTED", "source_file": "src/auth/oidc.rs", "source_location": "L232", "weight": 1.0}, {"source": "src_auth_oidc_rs", "target": "oidc_exchange_code_with_pkce", "relation": "contains", "confidence": "EXTRACTED", "source_file": "src/auth/oidc.rs", "source_location": "L241", "weight": 1.0}, {"source": "src_auth_oidc_rs", "target": "oidc_check_session", "relation": "contains", "confidence": "EXTRACTED", "source_file": "src/auth/oidc.rs", "source_location": "L300", "weight": 1.0}, {"source": "src_auth_oidc_rs", "target": "oidc_refresh_session", "relation": "contains", "confidence": "EXTRACTED", "source_file": "src/auth/oidc.rs", "source_location": "L344", "weight": 1.0}, {"source": "src_auth_oidc_rs", "target": "oidc_check_session_async", "relation": "contains", "confidence": "EXTRACTED", "source_file": "src/auth/oidc.rs", "source_location": "L401", "weight": 1.0}, {"source": "src_auth_oidc_rs", "target": "oidc_session_matches_issuer", "relation": "contains", "confidence": "EXTRACTED", "source_file": "src/auth/oidc.rs", "source_location": "L463", "weight": 1.0}, {"source": "src_auth_oidc_rs", "target": "oidc_generate_session_id", "relation": "contains", "confidence": "EXTRACTED", "source_file": "src/auth/oidc.rs", "source_location": "L471", "weight": 1.0}, {"source": "src_auth_oidc_rs", "target": "oidc_extract_cookie", "relation": "contains", "confidence": "EXTRACTED", "source_file": "src/auth/oidc.rs", "source_location": "L482", "weight": 1.0}, {"source": "src_auth_oidc_rs", "target": "oidc_extract_sub_from_id_token", "relation": "contains", "confidence": "EXTRACTED", "source_file": "src/auth/oidc.rs", "source_location": "L505", "weight": 1.0}, {"source": "src_auth_oidc_rs", "target": "oidc_urlencoded", "relation": "contains", "confidence": "EXTRACTED", "source_file": "src/auth/oidc.rs", "source_location": "L523", "weight": 1.0}, {"source": "src_auth_oidc_rs", "target": "super", "relation": "imports_from", "confidence": "EXTRACTED", "source_file": "src/auth/oidc.rs", "source_location": "L536", "weight": 1.0}, {"source": "src_auth_oidc_rs", "target": "oidc_test_config", "relation": "contains", "confidence": "EXTRACTED", "source_file": "src/auth/oidc.rs", "source_location": "L538", "weight": 1.0}, {"source": "src_auth_oidc_rs", "target": "oidc_test_discovery", "relation": "contains", "confidence": "EXTRACTED", "source_file": "src/auth/oidc.rs", "source_location": "L548", "weight": 1.0}, {"source": "src_auth_oidc_rs", "target": "oidc_test_authorization_url_contains_params", "relation": "contains", "confidence": "EXTRACTED", "source_file": "src/auth/oidc.rs", "source_location": "L558", "weight": 1.0}, {"source": "src_auth_oidc_rs", "target": "oidc_test_authorization_url_default_scopes", "relation": "contains", "confidence": "EXTRACTED", "source_file": "src/auth/oidc.rs", "source_location": "L568", "weight": 1.0}, {"source": "src_auth_oidc_rs", "target": "oidc_test_new_session_store_empty", "relation": "contains", "confidence": "EXTRACTED", "source_file": "src/auth/oidc.rs", "source_location": "L576", "weight": 1.0}, {"source": "src_auth_oidc_rs", "target": "oidc_test_check_session_no_cookie", "relation": "contains", "confidence": "EXTRACTED", "source_file": "src/auth/oidc.rs", "source_location": "L582", "weight": 1.0}, {"source": "src_auth_oidc_rs", "target": "oidc_test_check_session_invalid_session_id", "relation": "contains", "confidence": "EXTRACTED", "source_file": "src/auth/oidc.rs", "source_location": "L591", "weight": 1.0}, {"source": "src_auth_oidc_rs", "target": "oidc_test_check_session_valid", "relation": "contains", "confidence": "EXTRACTED", "source_file": "src/auth/oidc.rs", "source_location": "L603", "weight": 1.0}, {"source": "src_auth_oidc_rs", "target": "oidc_test_check_session_expired", "relation": "contains", "confidence": "EXTRACTED", "source_file": "src/auth/oidc.rs", "source_location": "L634", "weight": 1.0}, {"source": "src_auth_oidc_rs", "target": "oidc_test_extract_sub_from_id_token", "relation": "contains", "confidence": "EXTRACTED", "source_file": "src/auth/oidc.rs", "source_location": "L658", "weight": 1.0}, {"source": "src_auth_oidc_rs", "target": "oidc_test_extract_sub_from_id_token_malformed", "relation": "contains", "confidence": "EXTRACTED", "source_file": "src/auth/oidc.rs", "source_location": "L671", "weight": 1.0}, {"source": "src_auth_oidc_rs", "target": "oidc_test_urlencoded", "relation": "contains", "confidence": "EXTRACTED", "source_file": "src/auth/oidc.rs", "source_location": "L676", "weight": 1.0}, {"source": "src_auth_oidc_rs", "target": "oidc_test_generate_session_id_length", "relation": "contains", "confidence": "EXTRACTED", "source_file": "src/auth/oidc.rs", "source_location": "L683", "weight": 1.0}, {"source": "src_auth_oidc_rs", "target": "oidc_test_generate_session_id_unique", "relation": "contains", "confidence": "EXTRACTED", "source_file": "src/auth/oidc.rs", "source_location": "L689", "weight": 1.0}, {"source": "src_auth_oidc_rs", "target": "oidc_test_extract_cookie_present", "relation": "contains", "confidence": "EXTRACTED", "source_file": "src/auth/oidc.rs", "source_location": "L696", "weight": 1.0}, {"source": "src_auth_oidc_rs", "target": "oidc_test_extract_cookie_absent", "relation": "contains", "confidence": "EXTRACTED", "source_file": "src/auth/oidc.rs", "source_location": "L706", "weight": 1.0}, {"source": "src_auth_oidc_rs", "target": "oidc_test_session_matches_issuer_exact", "relation": "contains", "confidence": "EXTRACTED", "source_file": "src/auth/oidc.rs", "source_location": "L712", "weight": 1.0}, {"source": "src_auth_oidc_rs", "target": "oidc_test_session_matches_issuer_rejects_missing_issuer", "relation": "contains", "confidence": "EXTRACTED", "source_file": "src/auth/oidc.rs", "source_location": "L726", "weight": 1.0}, {"source": "src_auth_oidc_rs", "target": "oidc_test_session_refresh_token_stored", "relation": "contains", "confidence": "EXTRACTED", "source_file": "src/auth/oidc.rs", "source_location": "L740", "weight": 1.0}, {"source": "src_auth_oidc_rs", "target": "oidc_test_session_without_refresh_token", "relation": "contains", "confidence": "EXTRACTED", "source_file": "src/auth/oidc.rs", "source_location": "L755", "weight": 1.0}, {"source": "src_auth_oidc_rs", "target": "oidc_test_session_serialization_with_refresh_token", "relation": "contains", "confidence": "EXTRACTED", "source_file": "src/auth/oidc.rs", "source_location": "L769", "weight": 1.0}, {"source": "src_auth_oidc_rs", "target": "oidc_test_session_deserialization_without_refresh_token", "relation": "contains", "confidence": "EXTRACTED", "source_file": "src/auth/oidc.rs", "source_location": "L785", "weight": 1.0}, {"source": "src_auth_oidc_rs", "target": "oidc_test_check_session_async_expired_no_refresh", "relation": "contains", "confidence": "EXTRACTED", "source_file": "src/auth/oidc.rs", "source_location": "L793", "weight": 1.0}, {"source": "src_auth_oidc_rs", "target": "oidc_test_generate_code_verifier_length", "relation": "contains", "confidence": "EXTRACTED", "source_file": "src/auth/oidc.rs", "source_location": "L819", "weight": 1.0}, {"source": "src_auth_oidc_rs", "target": "oidc_test_generate_code_verifier_unique", "relation": "contains", "confidence": "EXTRACTED", "source_file": "src/auth/oidc.rs", "source_location": "L826", "weight": 1.0}, {"source": "src_auth_oidc_rs", "target": "oidc_test_compute_code_challenge_s256", "relation": "contains", "confidence": "EXTRACTED", "source_file": "src/auth/oidc.rs", "source_location": "L833", "weight": 1.0}, {"source": "src_auth_oidc_rs", "target": "oidc_test_authorization_url_with_pkce_includes_challenge", "relation": "contains", "confidence": "EXTRACTED", "source_file": "src/auth/oidc.rs", "source_location": "L843", "weight": 1.0}, {"source": "src_auth_oidc_rs", "target": "oidc_test_authorization_url_without_pkce_no_challenge", "relation": "contains", "confidence": "EXTRACTED", "source_file": "src/auth/oidc.rs", "source_location": "L858", "weight": 1.0}, {"source": "src_auth_oidc_rs", "target": "oidc_test_pkce_verifier_store_operations", "relation": "contains", "confidence": "EXTRACTED", "source_file": "src/auth/oidc.rs", "source_location": "L864", "weight": 1.0}, {"source": "oidc_authorization_url", "target": "oidc_authorization_url_with_pkce", "relation": "calls", "confidence": "EXTRACTED", "source_file": "src/auth/oidc.rs", "source_location": "L191", "weight": 1.0}, {"source": "oidc_authorization_url_with_pkce", "target": "oidc_generate_code_verifier", "relation": "calls", "confidence": "EXTRACTED", "source_file": "src/auth/oidc.rs", "source_location": "L217", "weight": 1.0}, {"source": "oidc_authorization_url_with_pkce", "target": "oidc_compute_code_challenge", "relation": "calls", "confidence": "EXTRACTED", "source_file": "src/auth/oidc.rs", "source_location": "L218", "weight": 1.0}, {"source": "oidc_exchange_code", "target": "oidc_exchange_code_with_pkce", "relation": "calls", "confidence": "EXTRACTED", "source_file": "src/auth/oidc.rs", "source_location": "L237", "weight": 1.0}, {"source": "oidc_exchange_code_with_pkce", "target": "oidc_extract_sub_from_id_token", "relation": "calls", "confidence": "EXTRACTED", "source_file": "src/auth/oidc.rs", "source_location": "L278", "weight": 1.0}, {"source": "oidc_check_session", "target": "oidc_extract_cookie", "relation": "calls", "confidence": "EXTRACTED", "source_file": "src/auth/oidc.rs", "source_location": "L305", "weight": 1.0}, {"source": "oidc_refresh_session", "target": "oidc_extract_sub_from_id_token", "relation": "calls", "confidence": "EXTRACTED", "source_file": "src/auth/oidc.rs", "source_location": "L375", "weight": 1.0}, {"source": "oidc_check_session_async", "target": "oidc_extract_cookie", "relation": "calls", "confidence": "EXTRACTED", "source_file": "src/auth/oidc.rs", "source_location": "L408", "weight": 1.0}, {"source": "oidc_check_session_async", "target": "oidc_refresh_session", "relation": "calls", "confidence": "EXTRACTED", "source_file": "src/auth/oidc.rs", "source_location": "L424", "weight": 1.0}, {"source": "oidc_test_authorization_url_contains_params", "target": "oidc_authorization_url", "relation": "calls", "confidence": "EXTRACTED", "source_file": "src/auth/oidc.rs", "source_location": "L559", "weight": 1.0}, {"source": "oidc_test_authorization_url_contains_params", "target": "oidc_test_config", "relation": "calls", "confidence": "EXTRACTED", "source_file": "src/auth/oidc.rs", "source_location": "L559", "weight": 1.0}, {"source": "oidc_test_authorization_url_contains_params", "target": "oidc_test_discovery", "relation": "calls", "confidence": "EXTRACTED", "source_file": "src/auth/oidc.rs", "source_location": "L559", "weight": 1.0}, {"source": "oidc_test_authorization_url_default_scopes", "target": "oidc_test_config", "relation": "calls", "confidence": "EXTRACTED", "source_file": "src/auth/oidc.rs", "source_location": "L569", "weight": 1.0}, {"source": "oidc_test_authorization_url_default_scopes", "target": "oidc_authorization_url", "relation": "calls", "confidence": "EXTRACTED", "source_file": "src/auth/oidc.rs", "source_location": "L571", "weight": 1.0}, {"source": "oidc_test_authorization_url_default_scopes", "target": "oidc_test_discovery", "relation": "calls", "confidence": "EXTRACTED", "source_file": "src/auth/oidc.rs", "source_location": "L571", "weight": 1.0}, {"source": "oidc_test_new_session_store_empty", "target": "oidc_new_session_store", "relation": "calls", "confidence": "EXTRACTED", "source_file": "src/auth/oidc.rs", "source_location": "L577", "weight": 1.0}, {"source": "oidc_test_check_session_no_cookie", "target": "oidc_new_session_store", "relation": "calls", "confidence": "EXTRACTED", "source_file": "src/auth/oidc.rs", "source_location": "L583", "weight": 1.0}, {"source": "oidc_test_check_session_no_cookie", "target": "oidc_check_session", "relation": "calls", "confidence": "EXTRACTED", "source_file": "src/auth/oidc.rs", "source_location": "L585", "weight": 1.0}, {"source": "oidc_test_check_session_invalid_session_id", "target": "oidc_new_session_store", "relation": "calls", "confidence": "EXTRACTED", "source_file": "src/auth/oidc.rs", "source_location": "L592", "weight": 1.0}, {"source": "oidc_test_check_session_invalid_session_id", "target": "oidc_check_session", "relation": "calls", "confidence": "EXTRACTED", "source_file": "src/auth/oidc.rs", "source_location": "L598", "weight": 1.0}, {"source": "oidc_test_check_session_valid", "target": "oidc_new_session_store", "relation": "calls", "confidence": "EXTRACTED", "source_file": "src/auth/oidc.rs", "source_location": "L604", "weight": 1.0}, {"source": "oidc_test_check_session_valid", "target": "oidc_check_session", "relation": "calls", "confidence": "EXTRACTED", "source_file": "src/auth/oidc.rs", "source_location": "L626", "weight": 1.0}, {"source": "oidc_test_check_session_expired", "target": "oidc_new_session_store", "relation": "calls", "confidence": "EXTRACTED", "source_file": "src/auth/oidc.rs", "source_location": "L635", "weight": 1.0}, {"source": "oidc_test_check_session_expired", "target": "oidc_check_session", "relation": "calls", "confidence": "EXTRACTED", "source_file": "src/auth/oidc.rs", "source_location": "L653", "weight": 1.0}, {"source": "oidc_test_generate_session_id_length", "target": "oidc_generate_session_id", "relation": "calls", "confidence": "EXTRACTED", "source_file": "src/auth/oidc.rs", "source_location": "L684", "weight": 1.0}, {"source": "oidc_test_generate_session_id_unique", "target": "oidc_generate_session_id", "relation": "calls", "confidence": "EXTRACTED", "source_file": "src/auth/oidc.rs", "source_location": "L690", "weight": 1.0}, {"source": "oidc_test_check_session_async_expired_no_refresh", "target": "oidc_new_session_store", "relation": "calls", "confidence": "EXTRACTED", "source_file": "src/auth/oidc.rs", "source_location": "L794", "weight": 1.0}, {"source": "oidc_test_check_session_async_expired_no_refresh", "target": "oidc_check_session_async", "relation": "calls", "confidence": "EXTRACTED", "source_file": "src/auth/oidc.rs", "source_location": "L812", "weight": 1.0}, {"source": "oidc_test_generate_code_verifier_length", "target": "oidc_generate_code_verifier", "relation": "calls", "confidence": "EXTRACTED", "source_file": "src/auth/oidc.rs", "source_location": "L820", "weight": 1.0}, {"source": "oidc_test_generate_code_verifier_unique", "target": "oidc_generate_code_verifier", "relation": "calls", "confidence": "EXTRACTED", "source_file": "src/auth/oidc.rs", "source_location": "L827", "weight": 1.0}, {"source": "oidc_test_compute_code_challenge_s256", "target": "oidc_compute_code_challenge", "relation": "calls", "confidence": "EXTRACTED", "source_file": "src/auth/oidc.rs", "source_location": "L838", "weight": 1.0}, {"source": "oidc_test_authorization_url_with_pkce_includes_challenge", "target": "oidc_new_pkce_verifier_store", "relation": "calls", "confidence": "EXTRACTED", "source_file": "src/auth/oidc.rs", "source_location": "L844", "weight": 1.0}, {"source": "oidc_test_authorization_url_with_pkce_includes_challenge", "target": "oidc_authorization_url_with_pkce", "relation": "calls", "confidence": "EXTRACTED", "source_file": "src/auth/oidc.rs", "source_location": "L845", "weight": 1.0}, {"source": "oidc_test_authorization_url_with_pkce_includes_challenge", "target": "oidc_test_config", "relation": "calls", "confidence": "EXTRACTED", "source_file": "src/auth/oidc.rs", "source_location": "L846", "weight": 1.0}, {"source": "oidc_test_authorization_url_with_pkce_includes_challenge", "target": "oidc_test_discovery", "relation": "calls", "confidence": "EXTRACTED", "source_file": "src/auth/oidc.rs", "source_location": "L847", "weight": 1.0}, {"source": "oidc_test_authorization_url_without_pkce_no_challenge", "target": "oidc_authorization_url", "relation": "calls", "confidence": "EXTRACTED", "source_file": "src/auth/oidc.rs", "source_location": "L859", "weight": 1.0}, {"source": "oidc_test_authorization_url_without_pkce_no_challenge", "target": "oidc_test_config", "relation": "calls", "confidence": "EXTRACTED", "source_file": "src/auth/oidc.rs", "source_location": "L859", "weight": 1.0}, {"source": "oidc_test_authorization_url_without_pkce_no_challenge", "target": "oidc_test_discovery", "relation": "calls", "confidence": "EXTRACTED", "source_file": "src/auth/oidc.rs", "source_location": "L859", "weight": 1.0}, {"source": "oidc_test_pkce_verifier_store_operations", "target": "oidc_new_pkce_verifier_store", "relation": "calls", "confidence": "EXTRACTED", "source_file": "src/auth/oidc.rs", "source_location": "L865", "weight": 1.0}], "raw_calls": [{"caller_nid": "oidc_new_session_store", "callee": "new", "source_file": "src/auth/oidc.rs", "source_location": "L97"}, {"caller_nid": "oidc_new_session_store", "callee": "new", "source_file": "src/auth/oidc.rs", "source_location": "L97"}, {"caller_nid": "oidc_sweep_expired_sessions", "callee": "as_secs", "source_file": "src/auth/oidc.rs", "source_location": "L110"}, {"caller_nid": "oidc_sweep_expired_sessions", "callee": "unwrap_or_default", "source_file": "src/auth/oidc.rs", "source_location": "L110"}, {"caller_nid": "oidc_sweep_expired_sessions", "callee": "duration_since", "source_file": "src/auth/oidc.rs", "source_location": "L110"}, {"caller_nid": "oidc_sweep_expired_sessions", "callee": "now", "source_file": "src/auth/oidc.rs", "source_location": "L110"}, {"caller_nid": "oidc_sweep_expired_sessions", "callee": "len", "source_file": "src/auth/oidc.rs", "source_location": "L114"}, {"caller_nid": "oidc_sweep_expired_sessions", "callee": "retain", "source_file": "src/auth/oidc.rs", "source_location": "L115"}, {"caller_nid": "oidc_sweep_expired_sessions", "callee": "saturating_sub", "source_file": "src/auth/oidc.rs", "source_location": "L116"}, {"caller_nid": "oidc_sweep_expired_sessions", "callee": "len", "source_file": "src/auth/oidc.rs", "source_location": "L116"}, {"caller_nid": "oidc_spawn_session_cleanup", "callee": "spawn", "source_file": "src/auth/oidc.rs", "source_location": "L126"}, {"caller_nid": "oidc_spawn_session_cleanup", "callee": "interval", "source_file": "src/auth/oidc.rs", "source_location": "L127"}, {"caller_nid": "oidc_spawn_session_cleanup", "callee": "from_secs", "source_file": "src/auth/oidc.rs", "source_location": "L127"}, {"caller_nid": "oidc_spawn_session_cleanup", "callee": "tick", "source_file": "src/auth/oidc.rs", "source_location": "L129"}, {"caller_nid": "oidc_discover", "callee": "map_err", "source_file": "src/auth/oidc.rs", "source_location": "L153"}, {"caller_nid": "oidc_discover", "callee": "get", "source_file": "src/auth/oidc.rs", "source_location": "L153"}, {"caller_nid": "oidc_discover", "callee": "map_err", "source_file": "src/auth/oidc.rs", "source_location": "L156"}, {"caller_nid": "oidc_new_pkce_verifier_store", "callee": "new", "source_file": "src/auth/oidc.rs", "source_location": "L166"}, {"caller_nid": "oidc_new_pkce_verifier_store", "callee": "new", "source_file": "src/auth/oidc.rs", "source_location": "L166"}, {"caller_nid": "oidc_generate_code_verifier", "callee": "fill", "source_file": "src/auth/oidc.rs", "source_location": "L173"}, {"caller_nid": "oidc_generate_code_verifier", "callee": "rng", "source_file": "src/auth/oidc.rs", "source_location": "L173"}, {"caller_nid": "oidc_generate_code_verifier", "callee": "encode", "source_file": "src/auth/oidc.rs", "source_location": "L175"}, {"caller_nid": "oidc_compute_code_challenge", "callee": "digest", "source_file": "src/auth/oidc.rs", "source_location": "L181"}, {"caller_nid": "oidc_compute_code_challenge", "callee": "as_bytes", "source_file": "src/auth/oidc.rs", "source_location": "L181"}, {"caller_nid": "oidc_compute_code_challenge", "callee": "encode", "source_file": "src/auth/oidc.rs", "source_location": "L183"}, {"caller_nid": "oidc_authorization_url_with_pkce", "callee": "is_empty", "source_file": "src/auth/oidc.rs", "source_location": "L201"}, {"caller_nid": "oidc_authorization_url_with_pkce", "callee": "to_string", "source_file": "src/auth/oidc.rs", "source_location": "L202"}, {"caller_nid": "oidc_authorization_url_with_pkce", "callee": "join", "source_file": "src/auth/oidc.rs", "source_location": "L204"}, {"caller_nid": "oidc_authorization_url_with_pkce", "callee": "insert", "source_file": "src/auth/oidc.rs", "source_location": "L219"}, {"caller_nid": "oidc_authorization_url_with_pkce", "callee": "to_string", "source_file": "src/auth/oidc.rs", "source_location": "L219"}, {"caller_nid": "oidc_authorization_url_with_pkce", "callee": "push_str", "source_file": "src/auth/oidc.rs", "source_location": "L220"}, {"caller_nid": "oidc_exchange_code_with_pkce", "callee": "new", "source_file": "src/auth/oidc.rs", "source_location": "L247"}, {"caller_nid": "oidc_exchange_code_with_pkce", "callee": "push", "source_file": "src/auth/oidc.rs", "source_location": "L257"}, {"caller_nid": "oidc_exchange_code_with_pkce", "callee": "map_err", "source_file": "src/auth/oidc.rs", "source_location": "L260"}, {"caller_nid": "oidc_exchange_code_with_pkce", "callee": "send", "source_file": "src/auth/oidc.rs", "source_location": "L260"}, {"caller_nid": "oidc_exchange_code_with_pkce", "callee": "form", "source_file": "src/auth/oidc.rs", "source_location": "L260"}, {"caller_nid": "oidc_exchange_code_with_pkce", "callee": "post", "source_file": "src/auth/oidc.rs", "source_location": "L260"}, {"caller_nid": "oidc_exchange_code_with_pkce", "callee": "is_success", "source_file": "src/auth/oidc.rs", "source_location": "L267"}, {"caller_nid": "oidc_exchange_code_with_pkce", "callee": "status", "source_file": "src/auth/oidc.rs", "source_location": "L267"}, {"caller_nid": "oidc_exchange_code_with_pkce", "callee": "Err", "source_file": "src/auth/oidc.rs", "source_location": "L268"}, {"caller_nid": "oidc_exchange_code_with_pkce", "callee": "map_err", "source_file": "src/auth/oidc.rs", "source_location": "L271"}, {"caller_nid": "oidc_exchange_code_with_pkce", "callee": "json", "source_file": "src/auth/oidc.rs", "source_location": "L271"}, {"caller_nid": "oidc_exchange_code_with_pkce", "callee": "unwrap_or_else", "source_file": "src/auth/oidc.rs", "source_location": "L278"}, {"caller_nid": "oidc_exchange_code_with_pkce", "callee": "to_string", "source_file": "src/auth/oidc.rs", "source_location": "L278"}, {"caller_nid": "oidc_exchange_code_with_pkce", "callee": "to_string", "source_file": "src/auth/oidc.rs", "source_location": "L280"}, {"caller_nid": "oidc_exchange_code_with_pkce", "callee": "as_secs", "source_file": "src/auth/oidc.rs", "source_location": "L283"}, {"caller_nid": "oidc_exchange_code_with_pkce", "callee": "unwrap_or_default", "source_file": "src/auth/oidc.rs", "source_location": "L283"}, {"caller_nid": "oidc_exchange_code_with_pkce", "callee": "duration_since", "source_file": "src/auth/oidc.rs", "source_location": "L283"}, {"caller_nid": "oidc_exchange_code_with_pkce", "callee": "now", "source_file": "src/auth/oidc.rs", "source_location": "L283"}, {"caller_nid": "oidc_exchange_code_with_pkce", "callee": "Ok", "source_file": "src/auth/oidc.rs", "source_location": "L288"}, {"caller_nid": "oidc_exchange_code_with_pkce", "callee": "Some", "source_file": "src/auth/oidc.rs", "source_location": "L291"}, {"caller_nid": "oidc_exchange_code_with_pkce", "callee": "clone", "source_file": "src/auth/oidc.rs", "source_location": "L291"}, {"caller_nid": "oidc_exchange_code_with_pkce", "callee": "unwrap_or", "source_file": "src/auth/oidc.rs", "source_location": "L295"}, {"caller_nid": "oidc_check_session", "callee": "get", "source_file": "src/auth/oidc.rs", "source_location": "L309"}, {"caller_nid": "oidc_check_session", "callee": "as_secs", "source_file": "src/auth/oidc.rs", "source_location": "L310"}, {"caller_nid": "oidc_check_session", "callee": "unwrap_or_default", "source_file": "src/auth/oidc.rs", "source_location": "L310"}, {"caller_nid": "oidc_check_session", "callee": "duration_since", "source_file": "src/auth/oidc.rs", "source_location": "L310"}, {"caller_nid": "oidc_check_session", "callee": "now", "source_file": "src/auth/oidc.rs", "source_location": "L310"}, {"caller_nid": "oidc_check_session", "callee": "drop", "source_file": "src/auth/oidc.rs", "source_location": "L317"}, {"caller_nid": "oidc_check_session", "callee": "remove", "source_file": "src/auth/oidc.rs", "source_location": "L318"}, {"caller_nid": "oidc_check_session", "callee": "Denied", "source_file": "src/auth/oidc.rs", "source_location": "L320"}, {"caller_nid": "oidc_check_session", "callee": "Some", "source_file": "src/auth/oidc.rs", "source_location": "L324"}, {"caller_nid": "oidc_check_session", "callee": "clone", "source_file": "src/auth/oidc.rs", "source_location": "L324"}, {"caller_nid": "oidc_check_session", "callee": "Denied", "source_file": "src/auth/oidc.rs", "source_location": "L328"}, {"caller_nid": "oidc_check_session", "callee": "Denied", "source_file": "src/auth/oidc.rs", "source_location": "L334"}, {"caller_nid": "oidc_refresh_session", "callee": "new", "source_file": "src/auth/oidc.rs", "source_location": "L349"}, {"caller_nid": "oidc_refresh_session", "callee": "map_err", "source_file": "src/auth/oidc.rs", "source_location": "L358"}, {"caller_nid": "oidc_refresh_session", "callee": "send", "source_file": "src/auth/oidc.rs", "source_location": "L358"}, {"caller_nid": "oidc_refresh_session", "callee": "form", "source_file": "src/auth/oidc.rs", "source_location": "L358"}, {"caller_nid": "oidc_refresh_session", "callee": "post", "source_file": "src/auth/oidc.rs", "source_location": "L358"}, {"caller_nid": "oidc_refresh_session", "callee": "is_success", "source_file": "src/auth/oidc.rs", "source_location": "L365"}, {"caller_nid": "oidc_refresh_session", "callee": "status", "source_file": "src/auth/oidc.rs", "source_location": "L365"}, {"caller_nid": "oidc_refresh_session", "callee": "Err", "source_file": "src/auth/oidc.rs", "source_location": "L366"}, {"caller_nid": "oidc_refresh_session", "callee": "map_err", "source_file": "src/auth/oidc.rs", "source_location": "L369"}, {"caller_nid": "oidc_refresh_session", "callee": "json", "source_file": "src/auth/oidc.rs", "source_location": "L369"}, {"caller_nid": "oidc_refresh_session", "callee": "unwrap_or_else", "source_file": "src/auth/oidc.rs", "source_location": "L375"}, {"caller_nid": "oidc_refresh_session", "callee": "to_string", "source_file": "src/auth/oidc.rs", "source_location": "L375"}, {"caller_nid": "oidc_refresh_session", "callee": "to_string", "source_file": "src/auth/oidc.rs", "source_location": "L377"}, {"caller_nid": "oidc_refresh_session", "callee": "as_secs", "source_file": "src/auth/oidc.rs", "source_location": "L380"}, {"caller_nid": "oidc_refresh_session", "callee": "unwrap_or_default", "source_file": "src/auth/oidc.rs", "source_location": "L380"}, {"caller_nid": "oidc_refresh_session", "callee": "duration_since", "source_file": "src/auth/oidc.rs", "source_location": "L380"}, {"caller_nid": "oidc_refresh_session", "callee": "now", "source_file": "src/auth/oidc.rs", "source_location": "L380"}, {"caller_nid": "oidc_refresh_session", "callee": "Ok", "source_file": "src/auth/oidc.rs", "source_location": "L385"}, {"caller_nid": "oidc_refresh_session", "callee": "Some", "source_file": "src/auth/oidc.rs", "source_location": "L388"}, {"caller_nid": "oidc_refresh_session", "callee": "clone", "source_file": "src/auth/oidc.rs", "source_location": "L388"}, {"caller_nid": "oidc_refresh_session", "callee": "unwrap_or", "source_file": "src/auth/oidc.rs", "source_location": "L392"}, {"caller_nid": "oidc_check_session_async", "callee": "get", "source_file": "src/auth/oidc.rs", "source_location": "L412"}, {"caller_nid": "oidc_check_session_async", "callee": "as_secs", "source_file": "src/auth/oidc.rs", "source_location": "L413"}, {"caller_nid": "oidc_check_session_async", "callee": "unwrap_or_default", "source_file": "src/auth/oidc.rs", "source_location": "L413"}, {"caller_nid": "oidc_check_session_async", "callee": "duration_since", "source_file": "src/auth/oidc.rs", "source_location": "L413"}, {"caller_nid": "oidc_check_session_async", "callee": "now", "source_file": "src/auth/oidc.rs", "source_location": "L413"}, {"caller_nid": "oidc_check_session_async", "callee": "clone", "source_file": "src/auth/oidc.rs", "source_location": "L420"}, {"caller_nid": "oidc_check_session_async", "callee": "drop", "source_file": "src/auth/oidc.rs", "source_location": "L421"}, {"caller_nid": "oidc_check_session_async", "callee": "clone", "source_file": "src/auth/oidc.rs", "source_location": "L427"}, {"caller_nid": "oidc_check_session_async", "callee": "insert", "source_file": "src/auth/oidc.rs", "source_location": "L428"}, {"caller_nid": "oidc_check_session_async", "callee": "Some", "source_file": "src/auth/oidc.rs", "source_location": "L429"}, {"caller_nid": "oidc_check_session_async", "callee": "remove", "source_file": "src/auth/oidc.rs", "source_location": "L433"}, {"caller_nid": "oidc_check_session_async", "callee": "remove", "source_file": "src/auth/oidc.rs", "source_location": "L437"}, {"caller_nid": "oidc_check_session_async", "callee": "Denied", "source_file": "src/auth/oidc.rs", "source_location": "L441"}, {"caller_nid": "oidc_check_session_async", "callee": "Some", "source_file": "src/auth/oidc.rs", "source_location": "L445"}, {"caller_nid": "oidc_check_session_async", "callee": "clone", "source_file": "src/auth/oidc.rs", "source_location": "L445"}, {"caller_nid": "oidc_check_session_async", "callee": "Denied", "source_file": "src/auth/oidc.rs", "source_location": "L449"}, {"caller_nid": "oidc_check_session_async", "callee": "Denied", "source_file": "src/auth/oidc.rs", "source_location": "L455"}, {"caller_nid": "oidc_session_matches_issuer", "callee": "as_deref", "source_file": "src/auth/oidc.rs", "source_location": "L464"}, {"caller_nid": "oidc_session_matches_issuer", "callee": "trim_end_matches", "source_file": "src/auth/oidc.rs", "source_location": "L465"}, {"caller_nid": "oidc_session_matches_issuer", "callee": "trim_end_matches", "source_file": "src/auth/oidc.rs", "source_location": "L465"}, {"caller_nid": "oidc_generate_session_id", "callee": "fill", "source_file": "src/auth/oidc.rs", "source_location": "L474"}, {"caller_nid": "oidc_generate_session_id", "callee": "rng", "source_file": "src/auth/oidc.rs", "source_location": "L474"}, {"caller_nid": "oidc_generate_session_id", "callee": "collect", "source_file": "src/auth/oidc.rs", "source_location": "L475"}, {"caller_nid": "oidc_generate_session_id", "callee": "map", "source_file": "src/auth/oidc.rs", "source_location": "L475"}, {"caller_nid": "oidc_generate_session_id", "callee": "iter", "source_file": "src/auth/oidc.rs", "source_location": "L475"}, {"caller_nid": "oidc_extract_cookie", "callee": "and_then", "source_file": "src/auth/oidc.rs", "source_location": "L483"}, {"caller_nid": "oidc_extract_cookie", "callee": "and_then", "source_file": "src/auth/oidc.rs", "source_location": "L483"}, {"caller_nid": "oidc_extract_cookie", "callee": "get", "source_file": "src/auth/oidc.rs", "source_location": "L483"}, {"caller_nid": "oidc_extract_cookie", "callee": "ok", "source_file": "src/auth/oidc.rs", "source_location": "L485"}, {"caller_nid": "oidc_extract_cookie", "callee": "to_str", "source_file": "src/auth/oidc.rs", "source_location": "L485"}, {"caller_nid": "oidc_extract_cookie", "callee": "split", "source_file": "src/auth/oidc.rs", "source_location": "L487"}, {"caller_nid": "oidc_extract_cookie", "callee": "trim", "source_file": "src/auth/oidc.rs", "source_location": "L488"}, {"caller_nid": "oidc_extract_cookie", "callee": "strip_prefix", "source_file": "src/auth/oidc.rs", "source_location": "L489"}, {"caller_nid": "oidc_extract_cookie", "callee": "trim_start_matches", "source_file": "src/auth/oidc.rs", "source_location": "L490"}, {"caller_nid": "oidc_extract_cookie", "callee": "is_empty", "source_file": "src/auth/oidc.rs", "source_location": "L491"}, {"caller_nid": "oidc_extract_cookie", "callee": "Some", "source_file": "src/auth/oidc.rs", "source_location": "L492"}, {"caller_nid": "oidc_extract_cookie", "callee": "to_string", "source_file": "src/auth/oidc.rs", "source_location": "L492"}, {"caller_nid": "oidc_extract_sub_from_id_token", "callee": "collect", "source_file": "src/auth/oidc.rs", "source_location": "L506"}, {"caller_nid": "oidc_extract_sub_from_id_token", "callee": "split", "source_file": "src/auth/oidc.rs", "source_location": "L506"}, {"caller_nid": "oidc_extract_sub_from_id_token", "callee": "len", "source_file": "src/auth/oidc.rs", "source_location": "L507"}, {"caller_nid": "oidc_extract_sub_from_id_token", "callee": "ok", "source_file": "src/auth/oidc.rs", "source_location": "L511"}, {"caller_nid": "oidc_extract_sub_from_id_token", "callee": "decode", "source_file": "src/auth/oidc.rs", "source_location": "L511"}, {"caller_nid": "oidc_extract_sub_from_id_token", "callee": "ok", "source_file": "src/auth/oidc.rs", "source_location": "L514"}, {"caller_nid": "oidc_extract_sub_from_id_token", "callee": "from_slice", "source_file": "src/auth/oidc.rs", "source_location": "L514"}, {"caller_nid": "oidc_extract_sub_from_id_token", "callee": "map", "source_file": "src/auth/oidc.rs", "source_location": "L515"}, {"caller_nid": "oidc_extract_sub_from_id_token", "callee": "and_then", "source_file": "src/auth/oidc.rs", "source_location": "L515"}, {"caller_nid": "oidc_extract_sub_from_id_token", "callee": "get", "source_file": "src/auth/oidc.rs", "source_location": "L515"}, {"caller_nid": "oidc_extract_sub_from_id_token", "callee": "as_str", "source_file": "src/auth/oidc.rs", "source_location": "L515"}, {"caller_nid": "oidc_urlencoded", "callee": "replace", "source_file": "src/auth/oidc.rs", "source_location": "L524"}, {"caller_nid": "oidc_urlencoded", "callee": "replace", "source_file": "src/auth/oidc.rs", "source_location": "L524"}, {"caller_nid": "oidc_urlencoded", "callee": "replace", "source_file": "src/auth/oidc.rs", "source_location": "L524"}, {"caller_nid": "oidc_urlencoded", "callee": "replace", "source_file": "src/auth/oidc.rs", "source_location": "L524"}, {"caller_nid": "oidc_urlencoded", "callee": "replace", "source_file": "src/auth/oidc.rs", "source_location": "L524"}, {"caller_nid": "oidc_urlencoded", "callee": "replace", "source_file": "src/auth/oidc.rs", "source_location": "L524"}, {"caller_nid": "oidc_urlencoded", "callee": "replace", "source_file": "src/auth/oidc.rs", "source_location": "L524"}, {"caller_nid": "oidc_test_config", "callee": "to_string", "source_file": "src/auth/oidc.rs", "source_location": "L540"}, {"caller_nid": "oidc_test_config", "callee": "to_string", "source_file": "src/auth/oidc.rs", "source_location": "L541"}, {"caller_nid": "oidc_test_config", "callee": "to_string", "source_file": "src/auth/oidc.rs", "source_location": "L542"}, {"caller_nid": "oidc_test_config", "callee": "to_string", "source_file": "src/auth/oidc.rs", "source_location": "L543"}, {"caller_nid": "oidc_test_discovery", "callee": "to_string", "source_file": "src/auth/oidc.rs", "source_location": "L550"}, {"caller_nid": "oidc_test_discovery", "callee": "to_string", "source_file": "src/auth/oidc.rs", "source_location": "L551"}, {"caller_nid": "oidc_test_discovery", "callee": "Some", "source_file": "src/auth/oidc.rs", "source_location": "L552"}, {"caller_nid": "oidc_test_discovery", "callee": "to_string", "source_file": "src/auth/oidc.rs", "source_location": "L552"}, {"caller_nid": "oidc_test_discovery", "callee": "to_string", "source_file": "src/auth/oidc.rs", "source_location": "L553"}, {"caller_nid": "oidc_test_check_session_no_cookie", "callee": "new", "source_file": "src/auth/oidc.rs", "source_location": "L584"}, {"caller_nid": "oidc_test_check_session_invalid_session_id", "callee": "new", "source_file": "src/auth/oidc.rs", "source_location": "L593"}, {"caller_nid": "oidc_test_check_session_invalid_session_id", "callee": "insert", "source_file": "src/auth/oidc.rs", "source_location": "L594"}, {"caller_nid": "oidc_test_check_session_invalid_session_id", "callee": "unwrap", "source_file": "src/auth/oidc.rs", "source_location": "L596"}, {"caller_nid": "oidc_test_check_session_invalid_session_id", "callee": "parse", "source_file": "src/auth/oidc.rs", "source_location": "L596"}, {"caller_nid": "oidc_test_check_session_valid", "callee": "as_secs", "source_file": "src/auth/oidc.rs", "source_location": "L605"}, {"caller_nid": "oidc_test_check_session_valid", "callee": "unwrap", "source_file": "src/auth/oidc.rs", "source_location": "L605"}, {"caller_nid": "oidc_test_check_session_valid", "callee": "duration_since", "source_file": "src/auth/oidc.rs", "source_location": "L605"}, {"caller_nid": "oidc_test_check_session_valid", "callee": "now", "source_file": "src/auth/oidc.rs", "source_location": "L605"}, {"caller_nid": "oidc_test_check_session_valid", "callee": "insert", "source_file": "src/auth/oidc.rs", "source_location": "L609"}, {"caller_nid": "oidc_test_check_session_valid", "callee": "to_string", "source_file": "src/auth/oidc.rs", "source_location": "L610"}, {"caller_nid": "oidc_test_check_session_valid", "callee": "to_string", "source_file": "src/auth/oidc.rs", "source_location": "L612"}, {"caller_nid": "oidc_test_check_session_valid", "callee": "Some", "source_file": "src/auth/oidc.rs", "source_location": "L613"}, {"caller_nid": "oidc_test_check_session_valid", "callee": "to_string", "source_file": "src/auth/oidc.rs", "source_location": "L613"}, {"caller_nid": "oidc_test_check_session_valid", "callee": "Some", "source_file": "src/auth/oidc.rs", "source_location": "L614"}, {"caller_nid": "oidc_test_check_session_valid", "callee": "to_string", "source_file": "src/auth/oidc.rs", "source_location": "L614"}, {"caller_nid": "oidc_test_check_session_valid", "callee": "to_string", "source_file": "src/auth/oidc.rs", "source_location": "L615"}, {"caller_nid": "oidc_test_check_session_valid", "callee": "new", "source_file": "src/auth/oidc.rs", "source_location": "L621"}, {"caller_nid": "oidc_test_check_session_valid", "callee": "insert", "source_file": "src/auth/oidc.rs", "source_location": "L622"}, {"caller_nid": "oidc_test_check_session_valid", "callee": "unwrap", "source_file": "src/auth/oidc.rs", "source_location": "L624"}, {"caller_nid": "oidc_test_check_session_valid", "callee": "parse", "source_file": "src/auth/oidc.rs", "source_location": "L624"}, {"caller_nid": "oidc_test_check_session_valid", "callee": "unwrap", "source_file": "src/auth/oidc.rs", "source_location": "L628"}, {"caller_nid": "oidc_test_check_session_expired", "callee": "insert", "source_file": "src/auth/oidc.rs", "source_location": "L636"}, {"caller_nid": "oidc_test_check_session_expired", "callee": "to_string", "source_file": "src/auth/oidc.rs", "source_location": "L637"}, {"caller_nid": "oidc_test_check_session_expired", "callee": "to_string", "source_file": "src/auth/oidc.rs", "source_location": "L639"}, {"caller_nid": "oidc_test_check_session_expired", "callee": "Some", "source_file": "src/auth/oidc.rs", "source_location": "L641"}, {"caller_nid": "oidc_test_check_session_expired", "callee": "to_string", "source_file": "src/auth/oidc.rs", "source_location": "L641"}, {"caller_nid": "oidc_test_check_session_expired", "callee": "to_string", "source_file": "src/auth/oidc.rs", "source_location": "L642"}, {"caller_nid": "oidc_test_check_session_expired", "callee": "new", "source_file": "src/auth/oidc.rs", "source_location": "L648"}, {"caller_nid": "oidc_test_check_session_expired", "callee": "insert", "source_file": "src/auth/oidc.rs", "source_location": "L649"}, {"caller_nid": "oidc_test_check_session_expired", "callee": "unwrap", "source_file": "src/auth/oidc.rs", "source_location": "L651"}, {"caller_nid": "oidc_test_check_session_expired", "callee": "parse", "source_file": "src/auth/oidc.rs", "source_location": "L651"}, {"caller_nid": "oidc_test_extract_sub_from_id_token", "callee": "encode", "source_file": "src/auth/oidc.rs", "source_location": "L661"}, {"caller_nid": "oidc_test_extract_sub_from_id_token", "callee": "unwrap", "source_file": "src/auth/oidc.rs", "source_location": "L662"}, {"caller_nid": "oidc_test_extract_sub_from_id_token", "callee": "to_vec", "source_file": "src/auth/oidc.rs", "source_location": "L662"}, {"caller_nid": "oidc_test_extract_cookie_present", "callee": "new", "source_file": "src/auth/oidc.rs", "source_location": "L697"}, {"caller_nid": "oidc_test_extract_cookie_present", "callee": "insert", "source_file": "src/auth/oidc.rs", "source_location": "L698"}, {"caller_nid": "oidc_test_extract_cookie_present", "callee": "unwrap", "source_file": "src/auth/oidc.rs", "source_location": "L700"}, {"caller_nid": "oidc_test_extract_cookie_present", "callee": "parse", "source_file": "src/auth/oidc.rs", "source_location": "L700"}, {"caller_nid": "oidc_test_extract_cookie_absent", "callee": "new", "source_file": "src/auth/oidc.rs", "source_location": "L707"}, {"caller_nid": "oidc_test_session_matches_issuer_exact", "callee": "to_string", "source_file": "src/auth/oidc.rs", "source_location": "L714"}, {"caller_nid": "oidc_test_session_matches_issuer_exact", "callee": "Some", "source_file": "src/auth/oidc.rs", "source_location": "L716"}, {"caller_nid": "oidc_test_session_matches_issuer_exact", "callee": "to_string", "source_file": "src/auth/oidc.rs", "source_location": "L716"}, {"caller_nid": "oidc_test_session_matches_issuer_exact", "callee": "to_string", "source_file": "src/auth/oidc.rs", "source_location": "L717"}, {"caller_nid": "oidc_test_session_matches_issuer_rejects_missing_issuer", "callee": "to_string", "source_file": "src/auth/oidc.rs", "source_location": "L728"}, {"caller_nid": "oidc_test_session_matches_issuer_rejects_missing_issuer", "callee": "to_string", "source_file": "src/auth/oidc.rs", "source_location": "L731"}, {"caller_nid": "oidc_test_session_refresh_token_stored", "callee": "to_string", "source_file": "src/auth/oidc.rs", "source_location": "L743"}, {"caller_nid": "oidc_test_session_refresh_token_stored", "callee": "Some", "source_file": "src/auth/oidc.rs", "source_location": "L745"}, {"caller_nid": "oidc_test_session_refresh_token_stored", "callee": "to_string", "source_file": "src/auth/oidc.rs", "source_location": "L745"}, {"caller_nid": "oidc_test_session_refresh_token_stored", "callee": "to_string", "source_file": "src/auth/oidc.rs", "source_location": "L746"}, {"caller_nid": "oidc_test_session_refresh_token_stored", "callee": "Some", "source_file": "src/auth/oidc.rs", "source_location": "L747"}, {"caller_nid": "oidc_test_session_refresh_token_stored", "callee": "to_string", "source_file": "src/auth/oidc.rs", "source_location": "L747"}, {"caller_nid": "oidc_test_session_without_refresh_token", "callee": "to_string", "source_file": "src/auth/oidc.rs", "source_location": "L757"}, {"caller_nid": "oidc_test_session_without_refresh_token", "callee": "to_string", "source_file": "src/auth/oidc.rs", "source_location": "L760"}, {"caller_nid": "oidc_test_session_serialization_with_refresh_token", "callee": "to_string", "source_file": "src/auth/oidc.rs", "source_location": "L771"}, {"caller_nid": "oidc_test_session_serialization_with_refresh_token", "callee": "to_string", "source_file": "src/auth/oidc.rs", "source_location": "L774"}, {"caller_nid": "oidc_test_session_serialization_with_refresh_token", "callee": "Some", "source_file": "src/auth/oidc.rs", "source_location": "L775"}, {"caller_nid": "oidc_test_session_serialization_with_refresh_token", "callee": "to_string", "source_file": "src/auth/oidc.rs", "source_location": "L775"}, {"caller_nid": "oidc_test_session_serialization_with_refresh_token", "callee": "unwrap", "source_file": "src/auth/oidc.rs", "source_location": "L779"}, {"caller_nid": "oidc_test_session_serialization_with_refresh_token", "callee": "to_string", "source_file": "src/auth/oidc.rs", "source_location": "L779"}, {"caller_nid": "oidc_test_session_serialization_with_refresh_token", "callee": "unwrap", "source_file": "src/auth/oidc.rs", "source_location": "L780"}, {"caller_nid": "oidc_test_session_serialization_with_refresh_token", "callee": "from_str", "source_file": "src/auth/oidc.rs", "source_location": "L780"}, {"caller_nid": "oidc_test_session_deserialization_without_refresh_token", "callee": "unwrap", "source_file": "src/auth/oidc.rs", "source_location": "L788"}, {"caller_nid": "oidc_test_session_deserialization_without_refresh_token", "callee": "from_str", "source_file": "src/auth/oidc.rs", "source_location": "L788"}, {"caller_nid": "oidc_test_check_session_async_expired_no_refresh", "callee": "insert", "source_file": "src/auth/oidc.rs", "source_location": "L795"}, {"caller_nid": "oidc_test_check_session_async_expired_no_refresh", "callee": "to_string", "source_file": "src/auth/oidc.rs", "source_location": "L796"}, {"caller_nid": "oidc_test_check_session_async_expired_no_refresh", "callee": "to_string", "source_file": "src/auth/oidc.rs", "source_location": "L798"}, {"caller_nid": "oidc_test_check_session_async_expired_no_refresh", "callee": "to_string", "source_file": "src/auth/oidc.rs", "source_location": "L801"}, {"caller_nid": "oidc_test_check_session_async_expired_no_refresh", "callee": "new", "source_file": "src/auth/oidc.rs", "source_location": "L807"}, {"caller_nid": "oidc_test_check_session_async_expired_no_refresh", "callee": "insert", "source_file": "src/auth/oidc.rs", "source_location": "L808"}, {"caller_nid": "oidc_test_check_session_async_expired_no_refresh", "callee": "unwrap", "source_file": "src/auth/oidc.rs", "source_location": "L810"}, {"caller_nid": "oidc_test_check_session_async_expired_no_refresh", "callee": "parse", "source_file": "src/auth/oidc.rs", "source_location": "L810"}, {"caller_nid": "oidc_test_authorization_url_with_pkce_includes_challenge", "callee": "Some", "source_file": "src/auth/oidc.rs", "source_location": "L849"}, {"caller_nid": "oidc_test_pkce_verifier_store_operations", "callee": "insert", "source_file": "src/auth/oidc.rs", "source_location": "L867"}, {"caller_nid": "oidc_test_pkce_verifier_store_operations", "callee": "to_string", "source_file": "src/auth/oidc.rs", "source_location": "L867"}, {"caller_nid": "oidc_test_pkce_verifier_store_operations", "callee": "to_string", "source_file": "src/auth/oidc.rs", "source_location": "L867"}, {"caller_nid": "oidc_test_pkce_verifier_store_operations", "callee": "map", "source_file": "src/auth/oidc.rs", "source_location": "L869"}, {"caller_nid": "oidc_test_pkce_verifier_store_operations", "callee": "remove", "source_file": "src/auth/oidc.rs", "source_location": "L869"}]}